pyaoc/__init__.py
pyaoc/__main__.py
pyaoc/cli.py
pyaoc/commands.py
pyaoc/constants.py
pyaoc/py.typed
pyaoc/template.py
pyaoc/utils.py
python_aoc-0.1.6.dist-info/METADATA
python_aoc-0.1.6.dist-info/WHEEL
python_aoc-0.1.6.dist-info/entry_points.txt
python_aoc-0.1.6.dist-info/licenses/LICENSE
python_aoc-0.1.6.dist-info/RECORD
