Metadata-Version: 2.4
Name: python-aoc
Version: 0.1.6
Summary: A Python CLI and library for interacting with the Advent of Code API to fetch puzzles, download inputs, and submit answers.
Project-URL: Homepage, https://github.com/benjaminrall/python-aoc
Author-email: Benjamin Rall <benr2508@aol.com>
License-File: LICENSE
Classifier: License :: OSI Approved :: MIT License
Classifier: Operating System :: OS Independent
Classifier: Programming Language :: Python :: 3
Requires-Python: >=3.12
Requires-Dist: requests>=2.32.4
Requires-Dist: typer>=0.16.0
